collatelogs/__init__.py
collatelogs/__main__.py
collatelogs/apache_config.yaml
collatelogs/cli.py
collatelogs/collatelogs.py
collatelogs/config.yaml
collatelogs/example_config.yaml
collatelogs/handlers.py
collatelogs/logcollator.py
collatelogs/metahandlers.py
collatelogs/util.py
collatelogs-0.2.3.data/scripts/collatelogs
collatelogs-0.2.3.dist-info/LICENSE
collatelogs-0.2.3.dist-info/METADATA
collatelogs-0.2.3.dist-info/WHEEL
collatelogs-0.2.3.dist-info/top_level.txt
collatelogs-0.2.3.dist-info/zip-safe
collatelogs-0.2.3.dist-info/RECORD
